c12simulator_clients/__init__.py
c12simulator_clients/user_configs.py
c12simulator_clients/api/__init__.py
c12simulator_clients/api/client.py
c12simulator_clients/api/configs.py
c12simulator_clients/api/exceptions.py
c12simulator_clients/qiskit_back/__init__.py
c12simulator_clients/qiskit_back/c12sim_backend.py
c12simulator_clients/qiskit_back/c12sim_job.py
c12simulator_clients/qiskit_back/c12sim_provider.py
c12simulator_clients/qiskit_back/exceptions.py
c12simulator_clients-0.0.6.dist-info/METADATA
c12simulator_clients-0.0.6.dist-info/WHEEL
c12simulator_clients-0.0.6.dist-info/top_level.txt
c12simulator_clients-0.0.6.dist-info/RECORD
