Metadata-Version: 2.1
Name: c12simulator-clients
Version: 0.0.6
Summary: Different clients for access to the C12 simulator
Home-page: https://github.com/c12qe/c12simulator-clients
Author: C12 Quantum Electronics
Author-email: viktor@c12qe.com
License: MIT
Project-URL: Homepage, https://www.c12qe.com
Project-URL: Source code, https://github.com/c12qe/c12simulator-clients
Project-URL: Issues, https://github.com/c12qe/c12simulator-clients/issues
Project-URL: Documentation, https://github.com/c12qe/c12simulator-clients/tree/master/docs
Keywords: qiskit quantum c12 simulator
Classifier: Programming Language :: Python :: 3 :: Only
Classifier: Programming Language :: Python :: 3.7
Classifier: Programming Language :: Python :: 3.8
Classifier: Programming Language :: Python :: 3.9
Classifier: Programming Language :: Python :: 3.10
Classifier: Programming Language :: Python :: 3.11
Classifier: Intended Audience :: Developers
Classifier: Intended Audience :: Science/Research
Classifier: Operating System :: Microsoft :: Windows
Classifier: Operating System :: MacOS
Classifier: Operating System :: POSIX :: Linux
Classifier: Environment :: Console
Classifier: Topic :: Scientific/Engineering
Requires-Python: >=3.7
Requires-Dist: requests ~=2.28
Requires-Dist: qiskit ~=0.41
Requires-Dist: pydantic ~=1.10
